mvclib/__init__.py
mvclib/aes.py
mvclib/base58.py
mvclib/constants.py
mvclib/curve.py
mvclib/hash.py
mvclib/keys.py
mvclib/utils.py
mvclib/wallet.py
mvclib/hd/__init__.py
mvclib/hd/bip32.py
mvclib/hd/bip39.py
mvclib/hd/bip44.py
mvclib/hd/wordlist/chinese_simplified.txt
mvclib/hd/wordlist/english.txt
mvclib/script/__init__.py
mvclib/script/script.py
mvclib/script/type.py
mvclib/service/__init__.py
mvclib/service/mvcapi.py
mvclib/service/provider.py
mvclib/service/service.py
mvclib/transaction/__init__.py
mvclib/transaction/transaction.py
mvclib/transaction/unspent.py
mvclib-0.6.0.dist-info/LICENSE
mvclib-0.6.0.dist-info/METADATA
mvclib-0.6.0.dist-info/WHEEL
mvclib-0.6.0.dist-info/top_level.txt
mvclib-0.6.0.dist-info/RECORD
